{
  "version": "4.6.0",
  "flags": {},
  "shapes": [
    {
      "label": "8",
      "points": [
        [
          116.94805194805195,
          124.02597402597402
        ],
        [
          340.97402597402595,
          128.57142857142856
        ],
        [
          359.15584415584414,
          438.31168831168833
        ],
        [
          81.23376623376623,
          433.1168831168831
        ]
      ],
      "group_id": null,
      "shape_type": "polygon",
      "flags": {}
    }
  ],
  "imagePath": "007.jpg",
  "imageData": null,
  "imageHeight": 500,
  "imageWidth": 493
}